coqui_stt_ctcdecoder/_swigwrapper.cpython-36m-x86_64-linux-gnu.so
coqui_stt_ctcdecoder/swigwrapper.py
coqui_stt_ctcdecoder/__init__.py
coqui_stt_ctcdecoder-1.4.0.dist-info/top_level.txt
coqui_stt_ctcdecoder-1.4.0.dist-info/LICENSE.paddlepaddle
coqui_stt_ctcdecoder-1.4.0.dist-info/WHEEL
coqui_stt_ctcdecoder-1.4.0.dist-info/METADATA
coqui_stt_ctcdecoder-1.4.0.dist-info/RECORD
coqui_stt_ctcdecoder-1.4.0.dist-info/COPYING
coqui_stt_ctcdecoder-1.4.0.dist-info/LICENSE.parlance
