Metadata-Version: 2.1
Name: coqui-stt-ctcdecoder
Version: 1.4.0
Summary: Coqui STT Python decoder package.
Home-page: UNKNOWN
License: UNKNOWN
Platform: UNKNOWN
Requires-Dist: numpy (>=1.7.0)
